django_drip_marketing-0.4.0.dist-info/DESCRIPTION.rst
django_drip_marketing-0.4.0.dist-info/METADATA
django_drip_marketing-0.4.0.dist-info/RECORD
django_drip_marketing-0.4.0.dist-info/WHEEL
django_drip_marketing-0.4.0.dist-info/metadata.json
django_drip_marketing-0.4.0.dist-info/top_level.txt
drip_marketing/__init__.py
drip_marketing/admin.py
drip_marketing/apps.py
drip_marketing/models.py
drip_marketing/management/__init__.py
drip_marketing/management/commands/__init__.py
drip_marketing/management/commands/run_drips.py
drip_marketing/management/commands/send_drips.py
drip_marketing/migrations/0001_initial.py
drip_marketing/migrations/__init__.py
drip_marketing/static/drip_marketing/css/admin.css
drip_marketing/static/drip_marketing/js/admin.js
drip_marketing/templates/admin/drip_marketing/change_form.html
drip_marketing/templates/admin/drip_marketing/timeline.html
drip_marketing/templates/admin/drip_marketing/view.html
