Metadata-Version: 2.0
Name: django-drip-marketing
Version: 0.4.0
Summary: Drip marketing for Django
Home-page: https://github.com/namespace-ee/django-drip-marketing
Author: Madis Väin
Author-email: madis@namespace.ee
License: BSD
Keywords: django-drip-marketing
Platform: UNKNOWN
Classifier: Development Status :: 3 - Alpha
Classifier: Framework :: Django
Classifier: Framework :: Django :: 1.8
Classifier: Framework :: Django :: 1.9
Classifier: Framework :: Django :: 1.10
Classifier: Intended Audience :: Developers
Classifier: License :: OSI Approved :: BSD License
Classifier: Natural Language :: English
Classifier: Programming Language :: Python :: 2
Classifier: Programming Language :: Python :: 2.7
Classifier: Programming Language :: Python :: 3
Classifier: Programming Language :: Python :: 3.3
Classifier: Programming Language :: Python :: 3.4
Classifier: Programming Language :: Python :: 3.5
Requires-Dist: dateparser (>=0.6.0)
Requires-Dist: django (>=1.8)
Requires-Dist: premailer (>=3.0.1)
